serato_tools/__init__.py
serato_tools/crate.py
serato_tools/database_v2.py
serato_tools/smart_crate.py
serato_tools/track_autotags.py
serato_tools/track_beatgrid.py
serato_tools/track_cues_v1.py
serato_tools/track_cues_v2.py
serato_tools/track_gain.py
serato_tools/track_tagdump.py
serato_tools/track_waveform.py
serato_tools/usb_export.py
serato_tools/utils/__init__.py
serato_tools/utils/beatgrid_analyze.py
serato_tools/utils/bin_file_base.py
serato_tools/utils/crate_base.py
serato_tools/utils/track_tags.py
serato_tools/utils/ui.py
serato_tools-3.7.0.dist-info/METADATA
serato_tools-3.7.0.dist-info/WHEEL
serato_tools-3.7.0.dist-info/entry_points.txt
serato_tools-3.7.0.dist-info/top_level.txt
serato_tools-3.7.0.dist-info/RECORD
