Metadata-Version: 2.4
Name: serato-tools
Version: 3.7.0
Summary: Serato track metadata (cues, beatgrid, etc.) crate, smartcrate, library database, and modification; dynamic beatgrid analysis; and better USB export.
Author-email: bvandercar-vt <bvandercar@outlook.com>
License-Expression: MIT
Project-URL: Homepage, https://pypi.org/project/serato-tools/
Project-URL: Repository, https://github.com/bvandercar-vt/serato-tools
Project-URL: Issues, https://github.com/bvandercar-vt/serato-tools/issues
Keywords: serato,serato crate,serato smart crate,serato smartcrate,serato database,serato hotcues,serato cues,serato beatgrid,serato usb,serato usb export,serato usb sync
Requires-Python: >=3.12
Requires-Dist: mutagen
Requires-Dist: numpy
Requires-Dist: librosa
Requires-Dist: pillow>=0; python_version < "3.14"
Requires-Dist: pillow>=12; python_version >= "3.14"
Provides-Extra: track-tags
Requires-Dist: mutagen; extra == "track-tags"
Provides-Extra: waveform-drawing
Requires-Dist: pillow; extra == "waveform-drawing"
Provides-Extra: beatgrid-analysis
Requires-Dist: librosa; extra == "beatgrid-analysis"
Requires-Dist: numpy; extra == "beatgrid-analysis"
